{
  "generated_at": "2026-07-15T04:09:12+08:00",
  "timezone": "Asia/Kuala_Lumpur",
  "refresh_interval_hours": 4,
  "stories": [
    {
      "id": "2026-07-15-gaza-health-officials-say-israeli-airstrike-on-police-station-kills-8",
      "category": "world",
      "headline": "Gaza health officials say Israeli airstrike on police station kills 8",
      "summary": "Key points: An Israeli airstrike on a police station in northern Gaza killed eight people, Gaza authorities said, while Israel said it targeted Hamas militants.",
      "why_it_matters": "This is a global or regional development that may affect risk appetite, trade, energy, technology or geopolitics.",
      "published_at": "2026-07-15T03:55:18+08:00",
      "source_links": [
        {
          "name": "CNA Latest",
          "url": "https://www.channelnewsasia.com/world/israel-strike-gaza-police-station-eight-killed-hamas-6254391",
          "publisher_type": "news"
        },
        {
          "name": "X Channel NewsAsia",
          "url": "https://x.com/ChannelNewsAsia",
          "publisher_type": "social"
        },
        {
          "name": "Facebook Channel NewsAsia",
          "url": "https://www.facebook.com/ChannelNewsAsia",
          "publisher_type": "social"
        }
      ],
      "topics": [
        "latest update"
      ],
      "importance": 4,
      "confidence": "reported_unconfirmed"
    },
    {
      "id": "2026-07-14-from-private-messages-to-public-threats-how-australia-s-young-men-are-being-trappe",
      "category": "world",
      "headline": "From private messages to public threats: How Australia’s young men are being trapped online",
      "summary": "Key points: Young men and boys are being targeted for sexual extortion on social media platforms, Aust...",
      "why_it_matters": "This is a global or regional development that may affect risk appetite, trade, energy, technology or geopolitics.",
      "published_at": "2026-07-14T21:00:00+08:00",
      "source_links": [
        {
          "name": "Malay Mail World",
          "url": "https://www.malaymail.com/news/world/2026/07/14/from-private-messages-to-public-threats-how-australias-young-men-are-being-trapped-online/227563",
          "publisher_type": "news"
        }
      ],
      "topics": [
        "latest update"
      ],
      "importance": 4,
      "confidence": "reported_unconfirmed"
    },
    {
      "id": "2026-07-14-amid-rubble-and-despair-one-man-s-desperate-hunt-for-his-family",
      "category": "world",
      "headline": "Amid rubble and despair, one man’s desperate hunt for his family",
      "summary": "Key points: Ten days after Venezuela’s twin earthquakes reduced his high-rise apartmen...",
      "why_it_matters": "This is a global or regional development that may affect risk appetite, trade, energy, technology or geopolitics.",
      "published_at": "2026-07-14T21:00:00+08:00",
      "source_links": [
        {
          "name": "Malay Mail World",
          "url": "https://www.malaymail.com/news/world/2026/07/14/amid-rubble-and-despair-one-mans-desperate-hunt-for-his-family/227581",
          "publisher_type": "news"
        }
      ],
      "topics": [
        "latest update"
      ],
      "importance": 4,
      "confidence": "reported_unconfirmed"
    },
    {
      "id": "2026-07-14-a-ride-cut-short-motorcyclist-killed-in-collision-with-driver-who-allegedly-ran-re",
      "category": "malaysia",
      "headline": "A ride cut short: Motorcyclist killed in collision with driver who allegedly ran red light at Sungai Petani junction",
      "summary": "Key points: SUNGAI PETANI, July 14 — A motorcyclist was killed after his motorcycle crashed into a car suspected of running a...",
      "why_it_matters": "This is a Malaysia-focused development that can affect policy, public services, business conditions or local sentiment.",
      "published_at": "2026-07-14T20:26:56+08:00",
      "source_links": [
        {
          "name": "Malay Mail Malaysia",
          "url": "https://www.malaymail.com/news/malaysia/2026/07/14/a-ride-cut-short-motorcyclist-killed-in-collision-with-driver-who-allegedly-ran-red-light-at-sungai-petani-junction/227605",
          "publisher_type": "news"
        }
      ],
      "topics": [
        "latest update"
      ],
      "importance": 3,
      "confidence": "reported_unconfirmed"
    },
    {
      "id": "2026-07-14-ex-civil-servant-under-four-day-macc-remand-accused-of-using-11-people-s-details-t",
      "category": "malaysia",
      "headline": "Ex-civil servant under four-day MACC remand, accused of using 11 people’s details to pocket RM300,000 in aid payments",
      "summary": "Key points: KUALA LUMPUR, July 14 — The Kuala Lumpur Malaysian Anti-Corruption Commission (MACC) yesterday detained a former c...",
      "why_it_matters": "This is a Malaysia-focused development that can affect policy, public services, business conditions or local sentiment.",
      "published_at": "2026-07-14T20:15:12+08:00",
      "source_links": [
        {
          "name": "Malay Mail Malaysia",
          "url": "https://www.malaymail.com/news/malaysia/2026/07/14/ex-civil-servant-under-four-day-macc-remand-accused-of-using-11-peoples-details-to-pocket-rm300000-in-aid-payments/227604",
          "publisher_type": "news"
        }
      ],
      "topics": [
        "latest update"
      ],
      "importance": 3,
      "confidence": "reported_unconfirmed"
    },
    {
      "id": "2026-07-14-spanish-court-bars-pm-sanchez-s-brother-from-public-office-for-nine-years",
      "category": "world",
      "headline": "Spanish court bars PM Sanchez’s brother from public office for nine years",
      "summary": "Key points: A Spanish court today banned the brother of Prime Minister Pedro Sanchez from holding publ...",
      "why_it_matters": "This is a global or regional development that may affect risk appetite, trade, energy, technology or geopolitics.",
      "published_at": "2026-07-14T19:51:57+08:00",
      "source_links": [
        {
          "name": "Malay Mail World",
          "url": "https://www.malaymail.com/news/world/2026/07/14/spanish-court-bars-pm-sanchezs-brother-from-public-office-for-nine-years/227602",
          "publisher_type": "news"
        }
      ],
      "topics": [
        "latest update"
      ],
      "importance": 4,
      "confidence": "reported_unconfirmed"
    },
    {
      "id": "2026-07-14-port-klang-border-officer-gets-shooting-threat-while-on-duty",
      "category": "malaysia",
      "headline": "Port Klang border officer gets shooting threat while on duty",
      "summary": "Key points: SHAH ALAM, July 14 — An enforcement officer from the Port Klang Border Control and Protection Agency (AKPS) r...",
      "why_it_matters": "This is a Malaysia-focused development that can affect policy, public services, business conditions or local sentiment.",
      "published_at": "2026-07-14T19:47:29+08:00",
      "source_links": [
        {
          "name": "Malay Mail Malaysia",
          "url": "https://www.malaymail.com/news/malaysia/2026/07/14/port-klang-border-officer-gets-shooting-threat-while-on-duty/227601",
          "publisher_type": "news"
        }
      ],
      "topics": [
        "latest update"
      ],
      "importance": 3,
      "confidence": "reported_unconfirmed"
    },
    {
      "id": "2026-07-14-selangor-sultan-singapore-president-talk-urban-floods-sustainability-and-future-ci",
      "category": "malaysia",
      "headline": "Selangor Sultan, Singapore president talk urban floods, sustainability and future cities in state visit",
      "summary": "Key points: The Sultan of Selangor, Sultan Sharafuddin Idris Shah, today granted an audience to Singapore Pre...",
      "why_it_matters": "This is a Malaysia-focused development that can affect policy, public services, business conditions or local sentiment.",
      "published_at": "2026-07-14T19:40:06+08:00",
      "source_links": [
        {
          "name": "Malay Mail Malaysia",
          "url": "https://www.malaymail.com/news/malaysia/2026/07/14/selangor-sultan-singapore-president-talk-urban-floods-sustainability-and-future-cities-in-state-visit/227600",
          "publisher_type": "news"
        }
      ],
      "topics": [
        "latest update"
      ],
      "importance": 3,
      "confidence": "reported_unconfirmed"
    },
    {
      "id": "2026-07-14-three-days-in-office-two-days-remote-hybrid-work-starts-aug-1-for-civil-servants-n",
      "category": "malaysia",
      "headline": "Three days in office, two days remote: Hybrid work starts Aug 1 for civil servants, no long weekends allowed",
      "summary": "Key points: KUALA LUMPUR, July 14 — The implementation of the Work From Home (WFH) initiative for civil servants since mid-Apr...",
      "why_it_matters": "This is a Malaysia-focused development that can affect policy, public services, business conditions or local sentiment.",
      "published_at": "2026-07-14T19:31:40+08:00",
      "source_links": [
        {
          "name": "Malay Mail Malaysia",
          "url": "https://www.malaymail.com/news/malaysia/2026/07/14/three-days-in-office-two-days-remote-hybrid-work-starts-aug-1-for-civil-servants-no-long-weekends-allowed/227598",
          "publisher_type": "news"
        }
      ],
      "topics": [
        "latest update"
      ],
      "importance": 3,
      "confidence": "reported_unconfirmed"
    },
    {
      "id": "2026-07-14-rain-wind-and-thunderstorms-expected-in-parts-of-peninsula-and-sabah-and-sarawak-u",
      "category": "malaysia",
      "headline": "Rain, wind and thunderstorms expected in parts of peninsula and Sabah and Sarawak until 9pm",
      "summary": "Key points: KUALA LUMPUR, July 14 — The Malaysian Meteorological Department (MetMalaysia) has issued a warning for thunderstor...",
      "why_it_matters": "This is a Malaysia-focused development that can affect policy, public services, business conditions or local sentiment.",
      "published_at": "2026-07-14T19:22:02+08:00",
      "source_links": [
        {
          "name": "Malay Mail Malaysia",
          "url": "https://www.malaymail.com/news/malaysia/2026/07/14/rain-wind-and-thunderstorms-expected-in-parts-of-peninsula-and-sabah-and-sarawak-until-9pm/227599",
          "publisher_type": "news"
        }
      ],
      "topics": [
        "latest update"
      ],
      "importance": 3,
      "confidence": "reported_unconfirmed"
    },
    {
      "id": "2026-07-14-wct-insider-trading-case-ex-director-businessman-lose-appeals-as-appellate-court-r",
      "category": "malaysia",
      "headline": "WCT insider trading case: Ex-director, businessman lose appeals as appellate court rules RM5.83m penalty stands",
      "summary": "Key points: KUALA LUMPUR, July 14 — The Court of Appeal today upheld the High Court’s decision which found former deputy...",
      "why_it_matters": "This is a Malaysia-focused development that can affect policy, public services, business conditions or local sentiment.",
      "published_at": "2026-07-14T19:13:45+08:00",
      "source_links": [
        {
          "name": "Malay Mail Malaysia",
          "url": "https://www.malaymail.com/news/malaysia/2026/07/14/wct-insider-trading-case-ex-director-businessman-lose-appeals-as-appellate-court-rules-rm583m-penalty-stands/227592",
          "publisher_type": "news"
        }
      ],
      "topics": [
        "latest update"
      ],
      "importance": 3,
      "confidence": "reported_unconfirmed"
    },
    {
      "id": "2026-07-14-bangkok-blaze-raises-fresh-concerns-over-nightclub-safety-after-30-deaths",
      "category": "world",
      "headline": "Bangkok blaze raises fresh concerns over nightclub safety after 30 deaths",
      "summary": "Key points: The Bangkok bar that erupted into flames, killing 30 people, lacked some basic safet...",
      "why_it_matters": "This is a global or regional development that may affect risk appetite, trade, energy, technology or geopolitics.",
      "published_at": "2026-07-14T19:09:11+08:00",
      "source_links": [
        {
          "name": "Malay Mail World",
          "url": "https://www.malaymail.com/news/world/2026/07/14/bangkok-blaze-raises-fresh-concerns-over-nightclub-safety-after-30-deaths/227597",
          "publisher_type": "news"
        }
      ],
      "topics": [
        "latest update"
      ],
      "importance": 4,
      "confidence": "reported_unconfirmed"
    },
    {
      "id": "2026-07-14-ringgit-ends-lower-as-investors-await-us-inflation-data-amid-west-asia-tensions",
      "category": "markets_investment",
      "headline": "Ringgit ends lower as investors await US inflation data amid West Asia tensions",
      "summary": "Key points: KUALA LUMPUR, July 14 — The ringgit ended lower against the US dollar on Tuesday as investors stayed ca...",
      "why_it_matters": "This can influence markets, currency, rates, corporate earnings or investor positioning.",
      "published_at": "2026-07-14T19:05:33+08:00",
      "source_links": [
        {
          "name": "Malay Mail Money",
          "url": "https://www.malaymail.com/news/money/2026/07/14/ringgit-ends-lower-as-investors-await-us-inflation-data-amid-west-asia-tensions/227596",
          "publisher_type": "news"
        }
      ],
      "topics": [
        "kuala lumpur",
        "ringgit",
        "inflation",
        "asia"
      ],
      "importance": 4,
      "confidence": "reported_unconfirmed"
    },
    {
      "id": "2026-07-14-dewan-rakyat-approves-bill-providing-stronger-witness-protection-including-help-fo",
      "category": "malaysia",
      "headline": "Dewan Rakyat approves Bill providing stronger witness protection, including help for children",
      "summary": "Key points: KUALA LUMPUR, July 14 — The Dewan Rakyat today passed the Witness Protection (Amendment) Bill 2026, aimed at expan...",
      "why_it_matters": "This is a Malaysia-focused development that can affect policy, public services, business conditions or local sentiment.",
      "published_at": "2026-07-14T19:04:18+08:00",
      "source_links": [
        {
          "name": "Malay Mail Malaysia",
          "url": "https://www.malaymail.com/news/malaysia/2026/07/14/dewan-rakyat-approves-bill-providing-stronger-witness-protection-including-help-for-children/227593",
          "publisher_type": "news"
        }
      ],
      "topics": [
        "latest update"
      ],
      "importance": 3,
      "confidence": "reported_unconfirmed"
    },
    {
      "id": "2026-07-14-need-new-books-for-class-madani-vouchers-open-for-1-18m-university-students-tomorr",
      "category": "malaysia",
      "headline": "Need new books for class? Madani vouchers open for 1.18m university students tomorrow",
      "summary": "Key points: A total of 1.18 million Malaysian students at institutions of higher learning (IPTs) can begi...",
      "why_it_matters": "This is a Malaysia-focused development that can affect policy, public services, business conditions or local sentiment.",
      "published_at": "2026-07-14T18:57:43+08:00",
      "source_links": [
        {
          "name": "Malay Mail Malaysia",
          "url": "https://www.malaymail.com/news/malaysia/2026/07/14/need-new-books-for-class-madani-vouchers-open-for-118m-university-students-tomorrow/227594",
          "publisher_type": "news"
        }
      ],
      "topics": [
        "latest update"
      ],
      "importance": 3,
      "confidence": "reported_unconfirmed"
    },
    {
      "id": "2026-07-14-ec-studying-postal-voting-for-all-malaysian-voters-decision-expected-in-2027",
      "category": "malaysia",
      "headline": "EC studying postal voting for all Malaysian voters, decision expected in 2027",
      "summary": "Key points: KUALA LUMPUR, July 14 — The Election Commission (EC) is conducting a detailed study on the proposed implementation...",
      "why_it_matters": "This is a Malaysia-focused development that can affect policy, public services, business conditions or local sentiment.",
      "published_at": "2026-07-14T18:46:31+08:00",
      "source_links": [
        {
          "name": "Malay Mail Malaysia",
          "url": "https://www.malaymail.com/news/malaysia/2026/07/14/ec-studying-postal-voting-for-all-malaysian-voters-decision-expected-in-2027/227595",
          "publisher_type": "news"
        }
      ],
      "topics": [
        "latest update"
      ],
      "importance": 3,
      "confidence": "reported_unconfirmed"
    },
    {
      "id": "2026-07-14-anwar-urges-melaka-dap-to-reconsider-state-govt-exit-keep-working-until-election",
      "category": "malaysia",
      "headline": "Anwar urges Melaka DAP to reconsider state govt exit, keep working until election",
      "summary": "Key points: PORT DICKSON, July 14 — Prime Minister Datuk Seri Anwar Ibrahim has urged Melaka DAP to postpone its decision to w...",
      "why_it_matters": "This is a Malaysia-focused development that can affect policy, public services, business conditions or local sentiment.",
      "published_at": "2026-07-14T18:35:31+08:00",
      "source_links": [
        {
          "name": "Malay Mail Malaysia",
          "url": "https://www.malaymail.com/news/malaysia/2026/07/14/anwar-urges-melaka-dap-to-reconsider-state-govt-exit-keep-working-until-election/227591",
          "publisher_type": "news"
        }
      ],
      "topics": [
        "latest update"
      ],
      "importance": 3,
      "confidence": "reported_unconfirmed"
    },
    {
      "id": "2026-07-14-felda-land-rules-up-for-review-as-govt-looks-at-housing-needs-of-new-generation",
      "category": "malaysia",
      "headline": "Felda land rules up for review as govt looks at housing needs of new generation",
      "summary": "Key points: KUALA LUMPUR, July 14 — The government is reviewing improvements to the land administration mechanism under the La...",
      "why_it_matters": "This is a Malaysia-focused development that can affect policy, public services, business conditions or local sentiment.",
      "published_at": "2026-07-14T18:23:20+08:00",
      "source_links": [
        {
          "name": "Malay Mail Malaysia",
          "url": "https://www.malaymail.com/news/malaysia/2026/07/14/felda-land-rules-up-for-review-as-govt-looks-at-housing-needs-of-new-generation/227575",
          "publisher_type": "news"
        }
      ],
      "topics": [
        "latest update"
      ],
      "importance": 3,
      "confidence": "reported_unconfirmed"
    },
    {
      "id": "2026-07-14-can-selangor-feed-itself-food-valley-harvests-10-tonnes-as-state-builds-three-mont",
      "category": "malaysia",
      "headline": "Can Selangor feed itself? Food Valley harvests 10 tonnes as state builds three-month food buffer",
      "summary": "Key points: KUALA SELANGOR, July 14 — Selangor Food Valley (SFV) has produced more than 10 tonnes of various fruits and agricu...",
      "why_it_matters": "This is a Malaysia-focused development that can affect policy, public services, business conditions or local sentiment.",
      "published_at": "2026-07-14T18:14:11+08:00",
      "source_links": [
        {
          "name": "Malay Mail Malaysia",
          "url": "https://www.malaymail.com/news/malaysia/2026/07/14/can-selangor-feed-itself-food-valley-harvests-10-tonnes-as-state-builds-three-month-food-buffer/227576",
          "publisher_type": "news"
        }
      ],
      "topics": [
        "latest update"
      ],
      "importance": 3,
      "confidence": "reported_unconfirmed"
    },
    {
      "id": "2026-07-14-in-muhyiddin-s-trial-businessman-says-brother-donated-part-of-company-s-rm13-7m-to",
      "category": "malaysia",
      "headline": "In Muhyiddin’s trial, businessman says brother donated part of company’s RM13.7m to Bersatu without his knowledge",
      "summary": "Key points: KUALA LUMPUR, July 14 — Businessman Shahrin Shamsuddin today told the High Court that he only discovered his elder...",
      "why_it_matters": "This is a Malaysia-focused development that can affect policy, public services, business conditions or local sentiment.",
      "published_at": "2026-07-14T18:04:06+08:00",
      "source_links": [
        {
          "name": "Malay Mail Malaysia",
          "url": "https://www.malaymail.com/news/malaysia/2026/07/14/in-muhyiddins-trial-businessman-says-brother-donated-part-of-companys-rm137m-to-bersatu-without-his-knowledge/227588",
          "publisher_type": "news"
        }
      ],
      "topics": [
        "latest update"
      ],
      "importance": 3,
      "confidence": "reported_unconfirmed"
    },
    {
      "id": "2026-07-14-fat-leonard-seeks-trump-pardon-citing-cancer-and-financial-hardship",
      "category": "malaysia",
      "headline": "‘Fat Leonard’ seeks Trump pardon, citing cancer and financial hardship",
      "summary": "Key points: Former defence contractor Leonard Glenn Francis is reportedly seeking clemency fr...",
      "why_it_matters": "This is a Malaysia-focused development that can affect policy, public services, business conditions or local sentiment.",
      "published_at": "2026-07-14T17:52:26+08:00",
      "source_links": [
        {
          "name": "Malay Mail Malaysia",
          "url": "https://www.malaymail.com/news/malaysia/2026/07/14/fat-leonard-seeks-trump-pardon-cites-cancer-and-financial-hardship/227582",
          "publisher_type": "news"
        }
      ],
      "topics": [
        "latest update"
      ],
      "importance": 3,
      "confidence": "reported_unconfirmed"
    },
    {
      "id": "2026-07-14-too-popular-for-its-own-good-gof-seizes-7-200-suspected-smuggled-obuse-beauty-prod",
      "category": "malaysia",
      "headline": "Too popular for its own good? GOF seizes 7,200 suspected smuggled Obuse beauty products at Rantau Panjang jetty",
      "summary": "Key points: KOTA BHARU, July 14 — The General Operations Force (GOF) seized 7,200 cosmetics products worth an estimated RM144,...",
      "why_it_matters": "This is a Malaysia-focused development that can affect policy, public services, business conditions or local sentiment.",
      "published_at": "2026-07-14T17:42:06+08:00",
      "source_links": [
        {
          "name": "Malay Mail Malaysia",
          "url": "https://www.malaymail.com/news/malaysia/2026/07/14/too-popular-for-its-own-good-gof-seizes-7200-suspected-smuggled-obuse-beauty-products-at-rantau-panjang-jetty/227580",
          "publisher_type": "news"
        }
      ],
      "topics": [
        "latest update"
      ],
      "importance": 3,
      "confidence": "reported_unconfirmed"
    },
    {
      "id": "2026-07-14-are-you-registered-inquest-officer-in-zara-qairina-case-questions-expert-witness-c",
      "category": "malaysia",
      "headline": "‘Are you registered?’ Inquest officer in Zara Qairina case questions expert witness’ child psychology specialist status",
      "summary": "Key points: KOTA KINABALU, July 14 — The Coroner’s Court here was told that the 76th witness in the inquest into the dea...",
      "why_it_matters": "This is a Malaysia-focused development that can affect policy, public services, business conditions or local sentiment.",
      "published_at": "2026-07-14T17:23:49+08:00",
      "source_links": [
        {
          "name": "Malay Mail Malaysia",
          "url": "https://www.malaymail.com/news/malaysia/2026/07/14/are-you-registered-inquest-officer-in-zara-qairina-case-questions-expert-witness-child-psychology-specialist-status/227578",
          "publisher_type": "news"
        }
      ],
      "topics": [
        "latest update"
      ],
      "importance": 3,
      "confidence": "reported_unconfirmed"
    },
    {
      "id": "2026-07-14-macc-seeks-two-bangladeshi-men-for-ongoing-corruption-trial",
      "category": "malaysia",
      "headline": "MACC seeks two Bangladeshi men for ongoing corruption trial",
      "summary": "Key points: The Malaysian Anti-Corruption Commission (MACC) is tracking down two Bangladeshi men required...",
      "why_it_matters": "This is a Malaysia-focused development that can affect policy, public services, business conditions or local sentiment.",
      "published_at": "2026-07-14T17:19:18+08:00",
      "source_links": [
        {
          "name": "Malay Mail Malaysia",
          "url": "https://www.malaymail.com/news/malaysia/2026/07/14/macc-seeks-two-bangladeshi-men-for-ongoing-corruption-trial/227573",
          "publisher_type": "news"
        }
      ],
      "topics": [
        "latest update"
      ],
      "importance": 3,
      "confidence": "reported_unconfirmed"
    },
    {
      "id": "2026-07-14-two-years-on-the-run-ends-as-police-nab-robbery-suspect-in-kajang",
      "category": "malaysia",
      "headline": "Two years on the run ends as police nab robbery suspect in Kajang",
      "summary": "Key points: KUALA LUMPUR, July 14 — Police have arrested a local man suspected of involvement in a gang robbery at a condomini...",
      "why_it_matters": "This is a Malaysia-focused development that can affect policy, public services, business conditions or local sentiment.",
      "published_at": "2026-07-14T17:05:21+08:00",
      "source_links": [
        {
          "name": "Malay Mail Malaysia",
          "url": "https://www.malaymail.com/news/malaysia/2026/07/14/two-years-on-the-run-ends-as-police-nab-robbery-suspect-in-kajang/227574",
          "publisher_type": "news"
        }
      ],
      "topics": [
        "latest update"
      ],
      "importance": 3,
      "confidence": "reported_unconfirmed"
    },
    {
      "id": "2026-07-14-ag-pp-separation-bill-postponed-to-next-sitting-pending-presentation-to-conference",
      "category": "malaysia",
      "headline": "AG-PP separation Bill postponed to next sitting pending presentation to Conference of Rulers, says Azalina",
      "summary": "Key points: KUALA LUMPUR, July 14 — The second reading of the Constitution (Amendment) (No. 2) Bill 2026 on the separation of...",
      "why_it_matters": "This is a Malaysia-focused development that can affect policy, public services, business conditions or local sentiment.",
      "published_at": "2026-07-14T17:01:37+08:00",
      "source_links": [
        {
          "name": "Malay Mail Malaysia",
          "url": "https://www.malaymail.com/news/malaysia/2026/07/14/ag-pp-separation-bill-postponed-to-next-sitting-pending-presentation-to-conference-of-rulers-says-azalina/227572",
          "publisher_type": "news"
        }
      ],
      "topics": [
        "latest update"
      ],
      "importance": 3,
      "confidence": "reported_unconfirmed"
    },
    {
      "id": "2026-07-14-a-simple-lesson-from-syed-saddiq-case-if-something-belongs-to-you-keep-it-to-yours",
      "category": "malaysia",
      "headline": "A simple lesson from Syed Saddiq case: If something belongs to you, keep it to yourself — Hafiz Hassan",
      "summary": "Key points: JULY 14 — Muar MP Syed Saddiq bin Syed Abdul Rahman was charged with two charges under the Penal Code (PC) and two...",
      "why_it_matters": "This is a Malaysia-focused development that can affect policy, public services, business conditions or local sentiment.",
      "published_at": "2026-07-14T17:00:00+08:00",
      "source_links": [
        {
          "name": "Malay Mail Malaysia",
          "url": "https://www.malaymail.com/news/malaysia/2026/07/14/a-simple-lesson-from-syed-saddiq-case-if-something-belongs-to-you-keep-it-to-yourself-hafiz-hassan/227550",
          "publisher_type": "news"
        }
      ],
      "topics": [
        "latest update"
      ],
      "importance": 3,
      "confidence": "reported_unconfirmed"
    },
    {
      "id": "2026-07-14-man-65-charged-in-perlis-with-trafficking-39-9-litres-of-fentanyl",
      "category": "malaysia",
      "headline": "Man, 65, charged in Perlis with trafficking 39.9 litres of fentanyl",
      "summary": "Key points: An elderly man was charged in the Magistrate’s Court here today with trafficking 39.9 litr...",
      "why_it_matters": "This is a Malaysia-focused development that can affect policy, public services, business conditions or local sentiment.",
      "published_at": "2026-07-14T16:57:10+08:00",
      "source_links": [
        {
          "name": "Malay Mail Malaysia",
          "url": "https://www.malaymail.com/news/malaysia/2026/07/14/man-65-charged-in-perlis-with-trafficking-399-litres-of-fentanyl/227571",
          "publisher_type": "news"
        }
      ],
      "topics": [
        "latest update"
      ],
      "importance": 3,
      "confidence": "reported_unconfirmed"
    },
    {
      "id": "2026-07-14-melaka-to-add-up-to-seven-nominated-assemblymen-after-constitutional-amendment-cm-",
      "category": "malaysia",
      "headline": "Melaka to add up to seven nominated assemblymen after constitutional amendment, CM says no ‘back door’ to power",
      "summary": "Key points: The Melaka State Legislative Assembly today passed a Bill to amend the State Constitution to pav...",
      "why_it_matters": "This is a Malaysia-focused development that can affect policy, public services, business conditions or local sentiment.",
      "published_at": "2026-07-14T16:55:38+08:00",
      "source_links": [
        {
          "name": "Malay Mail Malaysia",
          "url": "https://www.malaymail.com/news/malaysia/2026/07/14/melaka-to-add-up-to-seven-nominated-assemblymen-after-constitutional-amendment/227569",
          "publisher_type": "news"
        }
      ],
      "topics": [
        "latest update"
      ],
      "importance": 3,
      "confidence": "reported_unconfirmed"
    },
    {
      "id": "2026-07-14-proton-x70-driver-70-pleads-not-guilty-to-causing-motorcyclist-s-death-in-pj-s-sec",
      "category": "malaysia",
      "headline": "Proton X70 driver, 70, pleads not guilty to causing motorcyclist’s death in PJ’s Section 17",
      "summary": "Key points: KUALA LUMPUR, July 14 — A senior citizen pleaded not guilty in the Petaling Jaya Magistrate’s Court today to...",
      "why_it_matters": "This is a Malaysia-focused development that can affect policy, public services, business conditions or local sentiment.",
      "published_at": "2026-07-14T16:52:33+08:00",
      "source_links": [
        {
          "name": "Malay Mail Malaysia",
          "url": "https://www.malaymail.com/news/malaysia/2026/07/14/proton-x70-driver-70-pleads-not-guilty-to-causing-motorcyclists-death-in-pjs-section-17/227568",
          "publisher_type": "news"
        }
      ],
      "topics": [
        "latest update"
      ],
      "importance": 3,
      "confidence": "reported_unconfirmed"
    },
    {
      "id": "2026-07-14-home-ministry-probes-alleged-immigration-misuse-involving-network-school-in-forest",
      "category": "malaysia",
      "headline": "Home Ministry probes alleged immigration misuse involving Network School in Forest City",
      "summary": "Key points: The Home Ministry has launched a comprehensive investigation into the operations of Network S...",
      "why_it_matters": "This is a Malaysia-focused development that can affect policy, public services, business conditions or local sentiment.",
      "published_at": "2026-07-14T16:14:11+08:00",
      "source_links": [
        {
          "name": "Malay Mail Malaysia",
          "url": "https://www.malaymail.com/news/malaysia/2026/07/14/home-ministry-probes-alleged-immigration-misuse-involving-network-school-in-forest-city/227564",
          "publisher_type": "news"
        }
      ],
      "topics": [
        "latest update"
      ],
      "importance": 3,
      "confidence": "reported_unconfirmed"
    },
    {
      "id": "2026-07-14-dap-quits-melaka-govt-in-protest-of-newly-passed-bill-that-allows-for-unelected-as",
      "category": "malaysia",
      "headline": "DAP quits Melaka govt in protest of newly passed bill that allows for unelected assemblymen - The Edge Malaysia",
      "summary": "Key points: DAP quits Melaka govt in protest of newly passed bill that allows for unelected assemblymen The Edge Malaysia",
      "why_it_matters": "This is a Malaysia-focused development that can affect policy, public services, business conditions or local sentiment.",
      "published_at": "2026-07-14T15:52:05+08:00",
      "source_links": [
        {
          "name": "The Edge Malaysia via Google News",
          "url": "https://news.google.com/rss/articles/CBMiUEFVX3lxTE42MzUwcVozekdLUUI1Rm1EeWViTGxfOTFpTjVyOE1PWXRyZ0Q0Vk1MUnRYdFN3dk9BTGUtSmtxVV90LURRNDkwWGI4cko5NmZJ?oc=5",
          "publisher_type": "news"
        },
        {
          "name": "X The Edge Malaysia",
          "url": "https://x.com/theedgemalaysia",
          "publisher_type": "social"
        },
        {
          "name": "Facebook The Edge Malaysia",
          "url": "https://www.facebook.com/theedgemalaysia",
          "publisher_type": "social"
        }
      ],
      "topics": [
        "latest update"
      ],
      "importance": 3,
      "confidence": "reported_unconfirmed"
    },
    {
      "id": "2026-07-14-between-rm80-and-rm250-for-fake-work-permits-kedah-police-uncover-alleged-kulim-ba",
      "category": "malaysia",
      "headline": "Between RM80 and RM250 for fake work permits: Kedah police uncover alleged Kulim-based document syndicate",
      "summary": "Key points: ALOR SETAR, July 14 — Kedah police have cracked down on a syndicate believed to be issuing fake work permits and U...",
      "why_it_matters": "This is a Malaysia-focused development that can affect policy, public services, business conditions or local sentiment.",
      "published_at": "2026-07-14T15:46:28+08:00",
      "source_links": [
        {
          "name": "Malay Mail Malaysia",
          "url": "https://www.malaymail.com/news/malaysia/2026/07/14/between-rm80-and-rm250-for-fake-work-permits-kedah-police-uncover-alleged-kulim-based-document-syndicate/227555",
          "publisher_type": "news"
        }
      ],
      "topics": [
        "latest update"
      ],
      "importance": 3,
      "confidence": "reported_unconfirmed"
    },
    {
      "id": "2026-07-14-south-korea-hikes-2026-growth-outlook-to-3pc-on-ai-chip-boom",
      "category": "markets_investment",
      "headline": "South Korea hikes 2026 growth outlook to 3pc on AI chip boom",
      "summary": "Key points: South Korea raised its 2026 growth forecast by one percentage point to three per cent today,...",
      "why_it_matters": "This can influence markets, currency, rates, corporate earnings or investor positioning.",
      "published_at": "2026-07-14T15:44:19+08:00",
      "source_links": [
        {
          "name": "Malay Mail Money",
          "url": "https://www.malaymail.com/news/money/2026/07/14/south-korea-hikes-2026-growth-outlook-to-3pc-on-ai-chip-boom/227560",
          "publisher_type": "news"
        }
      ],
      "topics": [
        "latest update"
      ],
      "importance": 4,
      "confidence": "reported_unconfirmed"
    },
    {
      "id": "2026-07-14-trump-says-reflecting-pool-to-be-refilled-after-repairs",
      "category": "world",
      "headline": "Trump says Reflecting Pool to be refilled after repairs",
      "summary": "Key points: US President Donald Trump said today the newly renovated Reflecting Pool in Washington was d...",
      "why_it_matters": "This is a global or regional development that may affect risk appetite, trade, energy, technology or geopolitics.",
      "published_at": "2026-07-14T15:38:31+08:00",
      "source_links": [
        {
          "name": "Malay Mail World",
          "url": "https://www.malaymail.com/news/world/2026/07/14/trump-says-reflecting-pool-to-be-refilled-after-repairs/227561",
          "publisher_type": "news"
        }
      ],
      "topics": [
        "latest update"
      ],
      "importance": 4,
      "confidence": "reported_unconfirmed"
    },
    {
      "id": "2026-07-14-tvet-2-0-to-get-industry-boost-with-direct-recognition-for-graduates",
      "category": "malaysia",
      "headline": "TVET 2.0 to get industry boost with direct recognition for graduates",
      "summary": "Key points: KUALA LUMPUR, July 14 — The implementation of Technical and Vocational Education and Training (TVET) 2.0 will be s...",
      "why_it_matters": "This is a Malaysia-focused development that can affect policy, public services, business conditions or local sentiment.",
      "published_at": "2026-07-14T15:37:21+08:00",
      "source_links": [
        {
          "name": "Malay Mail Malaysia",
          "url": "https://www.malaymail.com/news/malaysia/2026/07/14/tvet-20-to-get-industry-boost-with-direct-recognition-for-graduates/227553",
          "publisher_type": "news"
        }
      ],
      "topics": [
        "latest update"
      ],
      "importance": 3,
      "confidence": "reported_unconfirmed"
    },
    {
      "id": "2026-07-14-melaka-dap-quits-state-government-over-nominated-assemblymen-bill",
      "category": "malaysia",
      "headline": "Melaka DAP quits state government over nominated assemblymen Bill",
      "summary": "Key points: Melaka DAP today announced its withdrawal from the state government in protest against the passa...",
      "why_it_matters": "This is a Malaysia-focused development that can affect policy, public services, business conditions or local sentiment.",
      "published_at": "2026-07-14T15:36:26+08:00",
      "source_links": [
        {
          "name": "Malay Mail Malaysia",
          "url": "https://www.malaymail.com/news/malaysia/2026/07/14/melaka-dap-quits-state-government-over-nominated-assemblymen-bill/227557",
          "publisher_type": "news"
        }
      ],
      "topics": [
        "latest update"
      ],
      "importance": 3,
      "confidence": "verified"
    },
    {
      "id": "2026-07-14-young-malaysians-still-want-marriage-and-kids-but-rising-costs-are-delaying-those-",
      "category": "malaysia",
      "headline": "Young Malaysians still want marriage and kids, but rising costs are delaying those plans in 2026",
      "summary": "Key points: KUALA LUMPUR, July 14 — The majority of Malaysian youths still aspire to get married and have children, but econom...",
      "why_it_matters": "This is a Malaysia-focused development that can affect policy, public services, business conditions or local sentiment.",
      "published_at": "2026-07-14T15:31:48+08:00",
      "source_links": [
        {
          "name": "Malay Mail Malaysia",
          "url": "https://www.malaymail.com/news/malaysia/2026/07/14/young-malaysians-still-want-marriage-and-kids-but-rising-costs-are-delaying-those-plans-in-2026/227556",
          "publisher_type": "news"
        }
      ],
      "topics": [
        "latest update"
      ],
      "importance": 3,
      "confidence": "reported_unconfirmed"
    },
    {
      "id": "2026-07-14-watch-what-you-post-japan-tightens-social-media-rules-for-elections",
      "category": "world",
      "headline": "Watch what you post: Japan tightens social media rules for elections",
      "summary": "Key points: AI-generated images and videos will have to be marked as such under new rules on the use of...",
      "why_it_matters": "This is a global or regional development that may affect risk appetite, trade, energy, technology or geopolitics.",
      "published_at": "2026-07-14T15:29:35+08:00",
      "source_links": [
        {
          "name": "Malay Mail World",
          "url": "https://www.malaymail.com/news/world/2026/07/14/watch-what-you-post-japan-tightens-social-media-rules-for-elections/227552",
          "publisher_type": "news"
        }
      ],
      "topics": [
        "latest update"
      ],
      "importance": 4,
      "confidence": "reported_unconfirmed"
    },
    {
      "id": "2026-07-14-penang-s-eroding-shoreline-at-batu-ferringhi-gets-rm500-000-temporary-protection",
      "category": "malaysia",
      "headline": "Penang’s eroding shoreline at Batu Ferringhi gets RM500,000 temporary protection",
      "summary": "Key points: GEORGE TOWN, July 14 — A RM500,000 coastal erosion mitigation project is underway at Batu Ferringhi as a temporary...",
      "why_it_matters": "This is a Malaysia-focused development that can affect policy, public services, business conditions or local sentiment.",
      "published_at": "2026-07-14T15:16:28+08:00",
      "source_links": [
        {
          "name": "Malay Mail Malaysia",
          "url": "https://www.malaymail.com/news/malaysia/2026/07/14/penangs-eroding-shoreline-at-batu-ferringhi-gets-rm500000-temporary-protection/227551",
          "publisher_type": "news"
        }
      ],
      "topics": [
        "latest update"
      ],
      "importance": 3,
      "confidence": "reported_unconfirmed"
    },
    {
      "id": "2026-07-14-rosmah-sues-comedian-harith-iskander-over-alleged-defamatory-jokes-body-shaming-re",
      "category": "malaysia",
      "headline": "Rosmah sues comedian Harith Iskander over alleged defamatory jokes, body-shaming remarks in stand-up show",
      "summary": "Key points: KUALA LUMPUR, July 14 — Datin Seri Rosmah Mansor has filed a lawsuit against comedian and actor Harith Iskander, a...",
      "why_it_matters": "This is a Malaysia-focused development that can affect policy, public services, business conditions or local sentiment.",
      "published_at": "2026-07-14T15:11:48+08:00",
      "source_links": [
        {
          "name": "Malay Mail Malaysia",
          "url": "https://www.malaymail.com/news/malaysia/2026/07/14/rosmah-sues-comedian-harith-iskander-over-alleged-defamatory-jokes-body-shaming-remarks-in-stand-up-show/227549",
          "publisher_type": "news"
        }
      ],
      "topics": [
        "latest update"
      ],
      "importance": 3,
      "confidence": "reported_unconfirmed"
    },
    {
      "id": "2026-07-14-china-says-exports-soar-more-than-forecast-in-june",
      "category": "world",
      "headline": "China says exports soar more than forecast in June",
      "summary": "Key points: BEIJING, July 14 —China’s exports surged more than expected last month, with official data today showing tha...",
      "why_it_matters": "This is a global or regional development that may affect risk appetite, trade, energy, technology or geopolitics.",
      "published_at": "2026-07-14T15:00:21+08:00",
      "source_links": [
        {
          "name": "Malay Mail Money",
          "url": "https://www.malaymail.com/news/money/2026/07/14/china-says-exports-soar-more-than-forecast-in-june/227546",
          "publisher_type": "news"
        }
      ],
      "topics": [
        "latest update"
      ],
      "importance": 4,
      "confidence": "reported_unconfirmed"
    },
    {
      "id": "2026-07-14-works-ministry-explains-why-sabah-pan-borneo-highway-cost-went-from-rm12-86b-to-rm",
      "category": "malaysia",
      "headline": "Works Ministry explains why Sabah Pan Borneo Highway cost went from RM12.86b to RM24.89b",
      "summary": "Key points: KUALA LUMPUR, July 14 — A total of RM1.2 billion has been paid by the federal government for land compensation for...",
      "why_it_matters": "This is a Malaysia-focused development that can affect policy, public services, business conditions or local sentiment.",
      "published_at": "2026-07-14T15:00:04+08:00",
      "source_links": [
        {
          "name": "Malay Mail Malaysia",
          "url": "https://www.malaymail.com/news/malaysia/2026/07/14/works-ministry-explains-why-sabah-pan-borneo-highway-cost-went-from-rm1286b-to-rm2489b/227530",
          "publisher_type": "news"
        }
      ],
      "topics": [
        "latest update"
      ],
      "importance": 3,
      "confidence": "reported_unconfirmed"
    },
    {
      "id": "2026-07-14-malaysia-sends-condolences-as-zambry-honours-late-qatar-ruler-sheikh-hamad",
      "category": "malaysia",
      "headline": "Malaysia sends condolences as Zambry honours late Qatar ruler Sheikh Hamad",
      "summary": "Key points: KUALA LUMPUR, July 14 — Higher Education Minister Datuk Seri Dr Zambry Abd Kadir arrived in Doha, Qatar early Tues...",
      "why_it_matters": "This is a Malaysia-focused development that can affect policy, public services, business conditions or local sentiment.",
      "published_at": "2026-07-14T14:51:17+08:00",
      "source_links": [
        {
          "name": "Malay Mail Malaysia",
          "url": "https://www.malaymail.com/news/malaysia/2026/07/14/malaysia-sends-condolences-as-zambry-honours-late-qatar-ruler-sheikh-hamad/227531",
          "publisher_type": "news"
        }
      ],
      "topics": [
        "latest update"
      ],
      "importance": 3,
      "confidence": "reported_unconfirmed"
    },
    {
      "id": "2026-07-14-housing-for-all-rehda-pushes-for-smarter-planning-with-better-data",
      "category": "malaysia",
      "headline": "Housing for all? Rehda pushes for smarter planning with better data",
      "summary": "Key points: PETALING JAYA, July 14 — The Real Estate Housing Developers’ Association (Rehda) has called for a more dynam...",
      "why_it_matters": "This is a Malaysia-focused development that can affect policy, public services, business conditions or local sentiment.",
      "published_at": "2026-07-14T14:44:13+08:00",
      "source_links": [
        {
          "name": "Malay Mail Malaysia",
          "url": "https://www.malaymail.com/news/malaysia/2026/07/14/housing-for-all-rehda-pushes-for-smarter-planning-with-better-data/227532",
          "publisher_type": "news"
        }
      ],
      "topics": [
        "latest update"
      ],
      "importance": 3,
      "confidence": "reported_unconfirmed"
    },
    {
      "id": "2026-07-14-bursa-malaysia-midday-rally-index-up-0-86pc-amid-banking-stock-surge",
      "category": "markets_investment",
      "headline": "Bursa Malaysia midday rally: Index up 0.86pc amid banking stock surge",
      "summary": "Key points: KUALA LUMPUR, July 14 — Bursa Malaysia ended the morning session higher, with the benchmark index gaining 0.86 per...",
      "why_it_matters": "This can influence markets, currency, rates, corporate earnings or investor positioning.",
      "published_at": "2026-07-14T14:43:04+08:00",
      "source_links": [
        {
          "name": "Malay Mail Money",
          "url": "https://www.malaymail.com/news/money/2026/07/14/bursa-malaysia-midday-rally-index-up-086pc-amid-banking-stock-surge/227542",
          "publisher_type": "news"
        }
      ],
      "topics": [
        "malaysia",
        "kuala lumpur",
        "bursa",
        "stock"
      ],
      "importance": 4,
      "confidence": "reported_unconfirmed"
    },
    {
      "id": "2026-07-14-malaysia-to-work-with-new-thai-peace-envoy-to-advance-dialogue-efforts-in-southern",
      "category": "malaysia",
      "headline": "Malaysia to work with new Thai peace envoy to advance dialogue efforts in southern Thailand",
      "summary": "Key points: KUALA LUMPUR, July 14 — Malaysia will work closely with Thanut Suvarnananda, the newly appointed chief of the Peac...",
      "why_it_matters": "This is a Malaysia-focused development that can affect policy, public services, business conditions or local sentiment.",
      "published_at": "2026-07-14T14:32:29+08:00",
      "source_links": [
        {
          "name": "Malay Mail Malaysia",
          "url": "https://www.malaymail.com/news/malaysia/2026/07/14/malaysia-to-work-with-new-thai-peace-envoy-to-advance-dialogue-efforts-in-southern-thailand/227529",
          "publisher_type": "news"
        }
      ],
      "topics": [
        "latest update"
      ],
      "importance": 3,
      "confidence": "reported_unconfirmed"
    },
    {
      "id": "2026-07-14-families-claim-bodies-as-bangkok-fire-toll-rises-to-30",
      "category": "world",
      "headline": "Families claim bodies as Bangkok fire toll rises to 30",
      "summary": "Key points: Grieving relatives of the victims of a huge Bangkok bar fire claimed their bodies today as...",
      "why_it_matters": "This is a global or regional development that may affect risk appetite, trade, energy, technology or geopolitics.",
      "published_at": "2026-07-14T14:28:12+08:00",
      "source_links": [
        {
          "name": "Malay Mail World",
          "url": "https://www.malaymail.com/news/world/2026/07/14/families-claim-bodies-as-bangkok-fire-toll-rises-to-30/227539",
          "publisher_type": "news"
        }
      ],
      "topics": [
        "latest update"
      ],
      "importance": 4,
      "confidence": "reported_unconfirmed"
    },
    {
      "id": "2026-07-14-give-us-the-time-under-the-mandate-anwar-says-as-pressure-mounts-for-early-ge16-af",
      "category": "malaysia",
      "headline": "‘Give us the time under the mandate,’ Anwar says as pressure mounts for early GE16 after Johor polls",
      "summary": "Key points: KUALA LUMPUR, July 14 — Prime Minister Datuk Seri Anwar Ibrahim today brushed aside calls for an early general ele...",
      "why_it_matters": "This is a Malaysia-focused development that can affect policy, public services, business conditions or local sentiment.",
      "published_at": "2026-07-14T14:14:29+08:00",
      "source_links": [
        {
          "name": "Malay Mail Malaysia",
          "url": "https://www.malaymail.com/news/malaysia/2026/07/14/give-us-the-time-under-the-mandate-anwar-says-as-pressure-mounts-for-early-ge16-after-johor-polls/227536",
          "publisher_type": "news"
        }
      ],
      "topics": [
        "kuala lumpur",
        "anwar",
        "johor",
        "war"
      ],
      "importance": 3,
      "confidence": "reported_unconfirmed"
    },
    {
      "id": "2026-07-14-new-national-housing-policy-to-set-affordable-home-prices-using-local-income-data",
      "category": "malaysia",
      "headline": "New national housing policy to set affordable home prices using local income data",
      "summary": "Key points: KUALA LUMPUR, July 14 — The government plans to use local income and housing demand data to set affordable home pr...",
      "why_it_matters": "This is a Malaysia-focused development that can affect policy, public services, business conditions or local sentiment.",
      "published_at": "2026-07-14T13:55:47+08:00",
      "source_links": [
        {
          "name": "Malay Mail Malaysia",
          "url": "https://www.malaymail.com/news/malaysia/2026/07/14/new-national-housing-policy-to-set-affordable-home-prices-using-local-income-data/227533",
          "publisher_type": "news"
        }
      ],
      "topics": [
        "latest update"
      ],
      "importance": 3,
      "confidence": "reported_unconfirmed"
    },
    {
      "id": "2026-07-14-malaysia-to-work-closely-with-new-thai-peace-dialogue-chief-mohamed-khaled-bernama",
      "category": "malaysia",
      "headline": "Malaysia To Work Closely With New Thai Peace Dialogue Chief - Mohamed Khaled - Bernama",
      "summary": "Key points: Malaysia To Work Closely With New Thai Peace Dialogue Chief - Mohamed Khaled Bernama",
      "why_it_matters": "This is a Malaysia-focused development that can affect policy, public services, business conditions or local sentiment.",
      "published_at": "2026-07-14T13:51:33+08:00",
      "source_links": [
        {
          "name": "BERNAMA via Google News",
          "url": "https://news.google.com/rss/articles/CBMiWEFVX3lxTE1ZTmtoY3pmUWNwQzB1VWM0WmlDWHFxZ044TE1nc0Z3ZzIxMTNzdXFTWjhGYkxkWW8xRTEwMTdneENMUzl6RmFIemtxaWtoaDhDaFl6Z0pqbEw?oc=5",
          "publisher_type": "news"
        },
        {
          "name": "X BERNAMA",
          "url": "https://x.com/bernamadotcom",
          "publisher_type": "social"
        },
        {
          "name": "Facebook BERNAMA",
          "url": "https://www.facebook.com/BernamaTV",
          "publisher_type": "social"
        }
      ],
      "topics": [
        "latest update"
      ],
      "importance": 3,
      "confidence": "reported_unconfirmed"
    },
    {
      "id": "2026-07-14-housing-ministry-says-1-615-troubled-housing-projects-worth-rm150-86b-rehabilitate",
      "category": "malaysia",
      "headline": "Housing Ministry says 1,615 troubled housing projects worth RM150.86b rehabilitated since 2022",
      "summary": "Key points: KUALA LUMPUR, July 14 — The government rehabilitated 1,615 delayed, sick and abandoned housing projects involving...",
      "why_it_matters": "This is a Malaysia-focused development that can affect policy, public services, business conditions or local sentiment.",
      "published_at": "2026-07-14T13:43:34+08:00",
      "source_links": [
        {
          "name": "Malay Mail Malaysia",
          "url": "https://www.malaymail.com/news/malaysia/2026/07/14/housing-ministry-says-1615-troubled-housing-projects-worth-rm15086b-rehabilitated-since-2022/227528",
          "publisher_type": "news"
        }
      ],
      "topics": [
        "latest update"
      ],
      "importance": 3,
      "confidence": "reported_unconfirmed"
    },
    {
      "id": "2026-07-14-malaysia-thailand-border-zone-to-open-up-access-to-indochina-markets-says-anwar",
      "category": "malaysia",
      "headline": "Malaysia–Thailand border zone to open up access to Indochina markets, says Anwar",
      "summary": "Key points: KUALA LUMPUR, July 14 — The development of the Malaysia–Thailand Border Economic Zone (BEZ) will provide Mal...",
      "why_it_matters": "This is a Malaysia-focused development that can affect policy, public services, business conditions or local sentiment.",
      "published_at": "2026-07-14T13:43:13+08:00",
      "source_links": [
        {
          "name": "Malay Mail Malaysia",
          "url": "https://www.malaymail.com/news/malaysia/2026/07/14/malaysiathailand-border-zone-to-open-up-access-to-indochina-markets-says-anwar/227525",
          "publisher_type": "news"
        }
      ],
      "topics": [
        "malaysia",
        "kuala lumpur",
        "anwar",
        "market"
      ],
      "importance": 3,
      "confidence": "reported_unconfirmed"
    },
    {
      "id": "2026-07-14-ex-igp-musa-hassan-must-pay-rm250-000-to-hannah-yeoh-after-federal-court-rejects-a",
      "category": "malaysia",
      "headline": "Ex-IGP Musa Hassan must pay RM250,000 to Hannah Yeoh after Federal Court rejects appeal bid",
      "summary": "Key points: The Federal Court here today dismissed former Inspector-General of Police Tan Sri Musa Hassan...",
      "why_it_matters": "This is a Malaysia-focused development that can affect policy, public services, business conditions or local sentiment.",
      "published_at": "2026-07-14T13:39:33+08:00",
      "source_links": [
        {
          "name": "Malay Mail Malaysia",
          "url": "https://www.malaymail.com/news/malaysia/2026/07/14/ex-igp-musa-hassan-must-pay-rm250000-to-hannah-yeoh-after-federal-court-rejects-appeal-bid/227524",
          "publisher_type": "news"
        }
      ],
      "topics": [
        "latest update"
      ],
      "importance": 3,
      "confidence": "reported_unconfirmed"
    },
    {
      "id": "2026-07-14-king-receives-briefing-from-macc-chief-abdul-halim-on-commission-s-latest-developm",
      "category": "malaysia",
      "headline": "King receives briefing from MACC chief Abdul Halim on commission’s latest developments",
      "summary": "Key points: KUALA LUMPUR, July 14 — His Majesty Sultan Ibrahim, King of Malaysia, today granted an audience to Malaysian Anti-...",
      "why_it_matters": "This is a Malaysia-focused development that can affect policy, public services, business conditions or local sentiment.",
      "published_at": "2026-07-14T13:19:27+08:00",
      "source_links": [
        {
          "name": "Malay Mail Malaysia",
          "url": "https://www.malaymail.com/news/malaysia/2026/07/14/king-receives-briefing-from-macc-chief-abdul-halim-on-commissions-latest-developments/227514",
          "publisher_type": "news"
        }
      ],
      "topics": [
        "latest update"
      ],
      "importance": 3,
      "confidence": "reported_unconfirmed"
    },
    {
      "id": "2026-07-14-smoke-complaints-around-sungai-petani-leads-kedah-doe-to-illegal-bukit-banyan-wast",
      "category": "malaysia",
      "headline": "Smoke complaints around Sungai Petani leads Kedah DOE to illegal Bukit Banyan waste dump site",
      "summary": "Key points: SUNGAI PETANI, July 14 — The Kedah Department of Environment (DOE) has detected an illegal solid waste disposal si...",
      "why_it_matters": "This is a Malaysia-focused development that can affect policy, public services, business conditions or local sentiment.",
      "published_at": "2026-07-14T13:15:10+08:00",
      "source_links": [
        {
          "name": "Malay Mail Malaysia",
          "url": "https://www.malaymail.com/news/malaysia/2026/07/14/smoke-complaints-around-sungai-petani-leads-kedah-doe-to-illegal-bukit-banyan-waste-dump-site/227513",
          "publisher_type": "news"
        }
      ],
      "topics": [
        "latest update"
      ],
      "importance": 3,
      "confidence": "reported_unconfirmed"
    },
    {
      "id": "2026-07-14-meets-expectations-revised-ag-pp-separation-bill-wins-backing-from-previously-diss",
      "category": "malaysia",
      "headline": "‘Meets expectations’: Revised AG-PP separation Bill wins backing from previously dissenting PKR MPs",
      "summary": "Key points: KUALA LUMPUR, July 14 — Several PKR backbenchers who had objected to the original Bill to decouple the public pros...",
      "why_it_matters": "This is a Malaysia-focused development that can affect policy, public services, business conditions or local sentiment.",
      "published_at": "2026-07-14T13:07:46+08:00",
      "source_links": [
        {
          "name": "Malay Mail Malaysia",
          "url": "https://www.malaymail.com/news/malaysia/2026/07/14/meets-expectations-revised-ag-pp-separation-bill-wins-backing-from-previously-dissenting-pkr-mps/227520",
          "publisher_type": "news"
        }
      ],
      "topics": [
        "latest update"
      ],
      "importance": 3,
      "confidence": "reported_unconfirmed"
    },
    {
      "id": "2026-07-14-malaysia-s-transport-ministry-told-to-map-out-border-ports-penang-hub-to-smoothen-",
      "category": "malaysia",
      "headline": "Malaysia’s Transport Ministry told to map out border ports, Penang hub to smoothen trade with Thailand",
      "summary": "Key points: KUALA LUMPUR, July 14 — The Transport Ministry has been asked to discuss the use of ports at the Malaysia–Th...",
      "why_it_matters": "This is a Malaysia-focused development that can affect policy, public services, business conditions or local sentiment.",
      "published_at": "2026-07-14T13:07:24+08:00",
      "source_links": [
        {
          "name": "Malay Mail Malaysia",
          "url": "https://www.malaymail.com/news/malaysia/2026/07/14/malaysias-transport-ministry-told-to-map-out-border-ports-penang-hub-to-smoothen-trade-with-thailand/227515",
          "publisher_type": "news"
        }
      ],
      "topics": [
        "latest update"
      ],
      "importance": 3,
      "confidence": "reported_unconfirmed"
    },
    {
      "id": "2026-07-14-penang-s-juru-sungai-dua-traffic-project-on-track-for-2027-completion-nearly-29pc-",
      "category": "malaysia",
      "headline": "Penang’s Juru–Sungai Dua traffic project on track for 2027 completion, nearly 29pc built",
      "summary": "Key points: GEORGE TOWN, July 14 — The Juru–Sungai Dua Traffic Dispersal Project (PTJSD) continues to record positive pr...",
      "why_it_matters": "This is a Malaysia-focused development that can affect policy, public services, business conditions or local sentiment.",
      "published_at": "2026-07-14T12:56:50+08:00",
      "source_links": [
        {
          "name": "Malay Mail Malaysia",
          "url": "https://www.malaymail.com/news/malaysia/2026/07/14/penangs-jurusungai-dua-traffic-project-on-track-for-2027-completion-nearly-29pc-built/227516",
          "publisher_type": "news"
        }
      ],
      "topics": [
        "latest update"
      ],
      "importance": 3,
      "confidence": "reported_unconfirmed"
    },
    {
      "id": "2026-07-14-king-welcomes-six-new-foreign-envoys-at-istana-negara-appoints-five-malaysian-amba",
      "category": "malaysia",
      "headline": "King welcomes six new foreign envoys at Istana Negara, appoints five Malaysian ambassadors",
      "summary": "Key points: KUALA LUMPUR, July 14 — His Majesty, Sultan Ibrahim, King of Malaysia, received Letters of Credence of six heads o...",
      "why_it_matters": "This is a Malaysia-focused development that can affect policy, public services, business conditions or local sentiment.",
      "published_at": "2026-07-14T12:48:08+08:00",
      "source_links": [
        {
          "name": "Malay Mail Malaysia",
          "url": "https://www.malaymail.com/news/malaysia/2026/07/14/king-welcomes-six-new-foreign-envoys-at-istana-negara-appoints-five-malaysian-ambassadors/227518",
          "publisher_type": "news"
        }
      ],
      "topics": [
        "latest update"
      ],
      "importance": 3,
      "confidence": "reported_unconfirmed"
    }
  ]
}
